simsvi/__init__.py
simsvi/run_simulation.py
simsvi/simsvi.py
simsvi-0.1.3.dist-info/LICENSE
simsvi-0.1.3.dist-info/METADATA
simsvi-0.1.3.dist-info/WHEEL
simsvi-0.1.3.dist-info/RECORD
