Metadata-Version: 2.1
Name: simsvi
Version: 0.1.3
Summary: simulate SVI analysis in a simple way
License: MIT
Author: Koichi Ito
Requires-Python: >=3.9,<4.0
Classifier: License :: OSI Approved :: MIT License
Classifier: Programming Language :: Python :: 3
Classifier: Programming Language :: Python :: 3.9
Classifier: Programming Language :: Python :: 3.10
Classifier: Programming Language :: Python :: 3.11
Classifier: Programming Language :: Python :: 3.12
Requires-Dist: matplotlib (>=3.8.3,<4.0.0)
Requires-Dist: numpy (>=1.26.4,<2.0.0)
Requires-Dist: pandas (>=2.2.1,<3.0.0)
Requires-Dist: pytest (>=8.0.2,<9.0.0)
Requires-Dist: tqdm (>=4.66.2,<5.0.0)
